rcl_logging_spdlog/_dummy.cpython-313-x86_64-linux-gnu.so
ros_rcl_logging_spdlog-3.2.3.data/data/lib/librcl_logging_spdlog.so
ros_rcl_logging_spdlog-3.2.3.data/data/share/ament_index/resource_index/package_run_dependencies/rcl_logging_spdlog
ros_rcl_logging_spdlog-3.2.3.data/data/share/ament_index/resource_index/packages/rcl_logging_spdlog
ros_rcl_logging_spdlog-3.2.3.data/data/share/ament_index/resource_index/parent_prefix_path/rcl_logging_spdlog
ros_rcl_logging_spdlog-3.2.3.data/data/share/rcl_logging_spdlog/local_setup.bash
ros_rcl_logging_spdlog-3.2.3.data/data/share/rcl_logging_spdlog/local_setup.dsv
ros_rcl_logging_spdlog-3.2.3.data/data/share/rcl_logging_spdlog/local_setup.sh
ros_rcl_logging_spdlog-3.2.3.data/data/share/rcl_logging_spdlog/local_setup.zsh
ros_rcl_logging_spdlog-3.2.3.data/data/share/rcl_logging_spdlog/package.dsv
ros_rcl_logging_spdlog-3.2.3.data/data/share/rcl_logging_spdlog/package.xml
ros_rcl_logging_spdlog-3.2.3.data/data/share/rcl_logging_spdlog/cmake/ament_cmake_export_dependencies-extras.cmake
ros_rcl_logging_spdlog-3.2.3.data/data/share/rcl_logging_spdlog/cmake/ament_cmake_export_libraries-extras.cmake
ros_rcl_logging_spdlog-3.2.3.data/data/share/rcl_logging_spdlog/cmake/ament_cmake_export_targets-extras.cmake
ros_rcl_logging_spdlog-3.2.3.data/data/share/rcl_logging_spdlog/cmake/rcl_logging_spdlogConfig-version.cmake
ros_rcl_logging_spdlog-3.2.3.data/data/share/rcl_logging_spdlog/cmake/rcl_logging_spdlogConfig.cmake
ros_rcl_logging_spdlog-3.2.3.data/data/share/rcl_logging_spdlog/cmake/rcl_logging_spdlogExport-release.cmake
ros_rcl_logging_spdlog-3.2.3.data/data/share/rcl_logging_spdlog/cmake/rcl_logging_spdlogExport.cmake
ros_rcl_logging_spdlog-3.2.3.data/data/share/rcl_logging_spdlog/environment/ament_prefix_path.dsv
ros_rcl_logging_spdlog-3.2.3.data/data/share/rcl_logging_spdlog/environment/ament_prefix_path.sh
ros_rcl_logging_spdlog-3.2.3.data/data/share/rcl_logging_spdlog/environment/library_path.dsv
ros_rcl_logging_spdlog-3.2.3.dist-info/METADATA
ros_rcl_logging_spdlog-3.2.3.dist-info/WHEEL
ros_rcl_logging_spdlog-3.2.3.dist-info/top_level.txt
ros_rcl_logging_spdlog-3.2.3.dist-info/RECORD
