Metadata-Version: 2.4
Name: ros-rcl-logging-spdlog
Version: 3.2.3
Summary: ROS package `rcl_logging_spdlog` offers an implementation of logging functionality using spdlog, supporting message logging and level control.
Requires-Dist: ros-spdlog-vendor~=1.7.0
Requires-Dist: ros-rcpputils~=2.13.5
Requires-Dist: ros-rcutils~=6.9.8
Requires-Dist: ros-rcl-logging-interface~=3.2.3
Dynamic: description
Dynamic: description-content-type
Dynamic: requires-dist
Dynamic: summary
